[
  {
    "id": 1,
    "title": "Gaming Set",
    "date": "2024-11-01 10:30:00",
    "description": "A gaming PC order with essential components."
  },
  {
    "id": 2,
    "title": "Office Equipment",
    "date": "2024-10-15 14:15:00",
    "description": "Equipment for an office workstation."
  },
  {
    "id": 3,
    "title": "Basic Computer Kit",
    "date": "2024-09-20 09:45:00",
    "description": "A basic kit for assembling a home PC."
  },
  {
    "id": 4,
    "title": "Professional Design Setup",
    "date": "2024-11-12 11:20:00",
    "description": "A setup for professional graphic design work."
  },
  {
    "id": 5,
    "title": "Gaming Accessories",
    "date": "2024-10-28 16:00:00",
    "description": "Accessories for gaming enthusiasts."
  },
  {
    "id": 6,
    "title": "Custom PC Build",
    "date": "2024-11-05 12:00:00",
    "description": "A custom-built PC with unique specifications."
  }
]
